{"id": "dd-sportf-aman-2342", "name": "Spotify Streaming", "description": "Just like that only", "date": "2342", "source": "fgf", "license": "CC BY", "category": "categories", "about": "entertainment", "citation": "fgfgdf (2342). 'Spotify Streaming', https://github.com/thedivtagguy/desidatasets/tree/master/datasets/categories/entertainment/dd-sportf-aman-2342. Retrieved from fgf \n", "download_command": "download_data(name = 'dd-sportf-aman-2342')", "icon": "https://avatars.dicebear.com/api/jdenticon/dd-sportf-aman-2342.svg"}